{
  "details": {
    "step0Activation": null,
    "thresholdCleanup": {
      "observationSucceeded": true,
      "observedIdsCount": 6,
      "observedIds": [
        "834244a6-65eb-4e93-8e32-dd486b42f115",
        "e56b73d0-1b99-4709-aa0f-4dcf9ccf3efd",
        "ab2fb403-6752-415e-b33e-b427f915d7a0",
        "65762a45-8398-46ed-95b6-7b4bf378388b",
        "ebf90a2c-3743-419e-986f-c82f9c5da66d",
        "b27ea220-bef2-428c-accf-c02172169acb"
      ],
      "minRemaining": 2000,
      "updatedRecordObservedIds": {}
    },
    "thresholdReached": true,
    "backpressure": {
      "ratio": 1.1119333333333334,
      "waitMsApplied": 1000,
      "tokensAfterWait": 33358,
      "thresholdAfterWait": 30000,
      "isBufferingObservationAfterWait": false,
      "bufferedChunksAfterWait": 4
    },
    "totalPendingTokens": 254,
    "threshold": 30000,
    "effectiveObservationTokensThreshold": 40000,
    "currentObservationTokens": 1797,
    "otherThreadTokens": 0,
    "contextMessageCount": 2
  }
}
